medium_multiply/__init__.py
medium_multiply/multiplication.py
medium_multiply_adil/__init__.py
medium_multiply_adil/multiplication.py
medium_multiply_adil-0.1.3.dist-info/METADATA
medium_multiply_adil-0.1.3.dist-info/WHEEL
medium_multiply_adil-0.1.3.dist-info/top_level.txt
medium_multiply_adil-0.1.3.dist-info/RECORD
