Metadata-Version: 2.1
Name: medium_multiply_adil
Version: 0.1.3
Summary: Demo library
Home-page: https://medium-multiply.readthedocs.io/
Author: Adil Zhiyenbayev
Author-email: adil70722156@gmail.com
License: MIT
Classifier: Intended Audience :: Developers
Classifier: License :: OSI Approved :: MIT License
Classifier: Programming Language :: Python
Classifier: Programming Language :: Python :: 3
Classifier: Programming Language :: Python :: 3.6
Classifier: Programming Language :: Python :: 3.7
Classifier: Programming Language :: Python :: 3.8
Classifier: Programming Language :: Python :: 3.9
Classifier: Operating System :: OS Independent
Requires-Dist: numpy
